runremote/__main__.py
runremote-1.0.1.dist-info/LICENCE.md
runremote-1.0.1.dist-info/METADATA
runremote-1.0.1.dist-info/WHEEL
runremote-1.0.1.dist-info/top_level.txt
runremote-1.0.1.dist-info/RECORD
