Metadata-Version: 2.1
Name: runremote
Version: 1.0.1
Summary: Run executables remotely through ssh
Author-email: Highghlow <highghlow@proton.me>
Project-URL: Homepage, https://github.com/highghlow/RunRemote
Project-URL: Bug Tracker, https://github.com/highghlow/RunRemote/issues
Classifier: Programming Language :: Python :: 3
Classifier: License :: OSI Approved :: MIT License
Classifier: Operating System :: OS Independent
Requires-Python: >=3.7
License-File: LICENCE.md
